{
    "metadata": {
        "title": "پورتفولیوی من",
        "description": "این پورتفولیوی سارا جلال است | دولوپر فرانت اند"
    },
    "header": {
        "title": "سارا",
        "hireMe": "استخدامم کن",
        "links": [
            {
                "name": "خانه",
                "path": "/fa"
            },
            {
                "name": "سرویس ها",
                "path": "/fa/services"
            },
            {
                "name": "رزومه",
                "path": "/fa/resume"
            },
            {
                "name": "کار",
                "path": "/fa/work"
            },
            {
                "name": "ارتباط",
                "path": "/fa/contact"
            }
        ],
        "mode": {
            "dark": "دارک",
            "light": "لایت",
            "system": "سیستم"
        }
    },
    "home": {
        "title": "توسعه دهنده وب",
        "h1": "سلام. من",
        "span": "سارا جلال هستم",
        "about": "یافتن پاسخ‌ها همواره یکی از مهم‌ترین ارزش‌های زندگی من بوده است. اگرچه ممکن است در دانستن همه چیز بهترین نباشم، اما در ارائه راه‌حل‌ها و آموزش آن به دیگران بهترین هستم.",
        "downloadcv": "دانلود رزومه",
        "stats": [
            {
                "num": 3,
                "text": "سال تجربه"
            },
            {
                "num": 16,
                "text": "پروژه‌های تکمیل‌شده"
            },
            {
                "num": 10,
                "text": "فناوری‌های مهارت‌یافته"
            },
            {
                "num": 4000,
                "text": "مشارکت‌های گیت‌هاب"
            }
        ]
    },
    "services": {
        "services": [
            {
                "num": "01",
                "title": "توسعه وب فرانت‌اند",
                "description": "توسعه وب فرانت‌اند شامل طراحی و پیاده‌سازی رابط‌های کاربری است که کاربران با آن تعامل دارند. من با استفاده از React، Next.js و TypeScript، وب‌سایت‌های زیبا و کاربرپسند را ایجاد می‌کنم و بر تجربه کاربری تمرکز دارم.",
                "href": "",
                "active": true,
                "status": "فعال"
            },
            {
                "num": "02",
                "title": "مدیریت محصول وب",
                "description": "مدیریت محصولات وب شامل برنامه‌ریزی و اجرای پروژه‌های وب است. من توانایی در هدایت تیم‌ها و اطمینان از تحویل به‌موقع پروژه‌ها را دارم و همواره در تلاش برای بهینه‌سازی فرایندها هستم.",
                "href": "",
                "active": true,
                "status": "فعال"
            },
            {
                "num": "03",
                "title": "توسعه وردپرس",
                "description": "توسعه وب‌سایت‌های وردپرسی به من این امکان را می‌دهد که با استفاده از ابزارها و افزونه‌های موجود، وب‌سایت‌های پویا و قابل تنظیم ایجاد کنم. من تجربه طراحی و توسعه وب‌سایت‌های متنوع را دارم.",
                "href": "",
                "active": true,
                "status": "فعال"
            },
            {
                "num": "04",
                "title": "طراحی گرافیک",
                "description": "طراحی گرافیکی برای من به عنوان یک هنر جذاب شناخته می‌شود که با استفاده از نرم‌افزارهای مختلف، به ایجاد برندها و هویت بصری کمک می‌کند. (غیرفعال، اما همچنان در پروژه‌ها می‌توانم از آن بهره ببرم.)",
                "href": "",
                "active": false,
                "status": "غیرفعال"
            },
            {
                "num": "05",
                "title": "مدرس ریاضی",
                "description": "تدریس ریاضی و فیزیک به من مهارت‌های ارتباطی و آموزشی قوی را ارائه داد. من به دانش‌آموزان کمک می‌کردم تا مفاهیم پیچیده را درک کنند و آماده‌سازی برای کنکور را انجام دهند. (غیرفعال، اما پایه‌گذار مسیری برای یادگیری بود.)",
                "href": "",
                "active": false,
                "status": "غیرفعال"
            }
        ]
    },
    "resume": {
        "titles": {
            "experience": "تجربه",
            "education": "تحصیلات",
            "skills": "مهارت‌ها",
            "about": "درباره من"
        },
        "about": {
            "title": "درباره من",
            "description": "یافتن پاسخ‌ها همواره یکی از مهم‌ترین ارزش‌های زندگی من بوده است. اگرچه ممکن است در دانستن همه چیز بهترین نباشم، اما در ارائه راه‌حل‌ها و آموزش آن به دیگران بهترین هستم."
        },
        "info": [
            {
                "fieldName": "نام",
                "fieldValue": "سارا جلال"
            },
            {
                "fieldName": "تلفن",
                "fieldValue": "(98+) 903 134 6086"
            },
            {
                "fieldName": "تجربه",
                "fieldValue": "6+ سال"
            },
            {
                "fieldName": " میت",
                "fieldValue": "Sara.jalal.115@gmail.com"
            },
            {
                "fieldName": "ملیت",
                "fieldValue": "ایرانی/بحرینی"
            },
            {
                "fieldName": "ایمیل",
                "fieldValue": "Sara.jalal.115@gmail.com"
            },
            {
                "fieldName": "فریلنس",
                "fieldValue": "در دسترس"
            },
            {
                "fieldName": "زبان‌ها",
                "fieldValue": "انگلیسی، فارسی"
            }
        ],
        "experience": {
            "icon": "/images/resume/badge.svg",
            "title": "تجربه‌های من",
            "description": "",
            "items": [
                {
                    "company": "نیکات",
                    "companyLinkedInLink": "",
                    "position": "لید تیم توسعه",
                    "duration": "مرداد 1402 - اکنون"
                },
                {
                    "company": "نیکات",
                    "companyLinkedInLink": "",
                    "position": "توسعه‌دهنده فرانت‌اند",
                    "duration": "اسفند 1401 - اکنون"
                },
                {
                    "company": "مؤسسه ایده‌آل مکین",
                    "companyLinkedInLink": "",
                    "position": "توسعه‌دهنده فرانت‌اند",
                    "duration": "خرداد 1401 - بهمن 1401"
                },
                {
                    "company": "فریلنس",
                    "companyLinkedInLink": "",
                    "position": "توسعه‌دهنده وردپرس",
                    "duration": "1397 - اکنون"
                },
                {
                    "company": "فریلنس",
                    "companyLinkedInLink": "",
                    "position": "طراح گرافیک",
                    "duration": "1397 - 1401"
                },
                {
                    "company": "فریلنس",
                    "companyLinkedInLink": "",
                    "position": "معلم ریاضی",
                    "duration": "1397 - 1399"
                }
            ]
        },
        "education": {
            "icon": "/images/resume/cap.svg",
            "title": "تحصیلات من",
            "description": "لورم ایپسوم متن ساختگی با تولید سادگی نامفهوم از صنعت چاپ.",
            "items": [
                {
                    "Institution": "بوت‌کمپ برنامه‌نویسی مکین",
                    "companyLinkedInLink": "",
                    "position": "کارآموز توسعه فرانت‌اند",
                    "duration": "خرداد 1401 - بهمن 1401"
                },
                {
                    "Institution": "دانشگاه آزاد اسلامی واحد علوم و تحقیقات",
                    "companyLinkedInLink": "",
                    "position": "کارشناسی مهندسی نرم‌افزار",
                    "duration": "مهر 1397 - خرداد 2022"
                }
            ]
        },
        "skills": {
            "title": "مهارت های من",
            "description": ""
        }
    },
    "work": {
        "projects": [
            {
                "num": "09",
                "category": "فرانت‌اند",
                "title": "Nikaat/panel",
                "description": "یک پنل PWA ساده برای کاربران Nikaat/landing و Nikaat/cocofit-landing برای دسترسی به برنامه رژیم غذایی و تمرینات خود.",
                "stack": [
                    {
                        "name": "Typescript"
                    },
                    {
                        "name": "React"
                    },
                    {
                        "name": "Next"
                    },
                    {
                        "name": "NextPWA"
                    },
                    {
                        "name": "Tailwind"
                    },
                    {
                        "name": "Axios"
                    },
                    {
                        "name": "ReactQuery"
                    },
                    {
                        "name": "GOauth"
                    },
                    {
                        "name": "GoogleAnalytics"
                    }
                ],
                "image": "/images/work/thumb1.png",
                "live": "https://panel.matchadiet.com/",
                "github": "https://github.com/sararmjalal"
            },
            {
                "num": "08",
                "category": "فرانت‌اند",
                "title": "Nikaat/chatfit",
                "description": "یک کوییز ساده ساخته‌شده با استفاده از عناصر ارائه‌شده توسط API که انواع مختلفی از کوییزها را از طریق URL ارائه می‌دهد.",
                "stack": [
                    {
                        "name": "Typescript"
                    },
                    {
                        "name": "React"
                    },
                    {
                        "name": "Next"
                    },
                    {
                        "name": "Tailwind"
                    },
                    {
                        "name": "Axios"
                    },
                    {
                        "name": "ReactQuery"
                    }
                ],
                "image": "/images/work/thumb1.png",
                "live": "",
                "github": "https://github.com/sararmjalal"
            },
            {
                "num": "07",
                "category": "فرانت‌اند",
                "title": "Nikaat/maktab",
                "description": "یک وب‌سایت آموزشی که شامل پنل‌های جداگانه برای معلمان، دانش‌آموزان و غیره می‌باشد. دانش‌آموزان ثبت‌نام‌شده می‌توانند دوره‌ها را بگذرانند، آزمون‌های آنلاین بدهند، گواهی دریافت کنند، رزومه بسازند و به دنبال کار بگردند.",
                "stack": [
                    {
                        "name": "Javascript"
                    },
                    {
                        "name": "React"
                    },
                    {
                        "name": "Bootstrap"
                    },
                    {
                        "name": "ReactQuery"
                    },
                    {
                        "name": "ReduxToolkit"
                    },
                    {
                        "name": "Webpack.config"
                    }
                ],
                "image": "/images/work/thumb1.png",
                "live": "https://school.viracc.ir/",
                "github": "https://github.com/sararmjalal"
            },
            {
                "num": "06",
                "category": "فرانت‌اند",
                "title": "Nikaat/maktab-panel",
                "description": "پنلی مرتبط با Nikaat/maktab که تمام ویژگی‌ها را فعال می‌کند.",
                "stack": [
                    {
                        "name": "Javascript"
                    },
                    {
                        "name": "React"
                    },
                    {
                        "name": "Bootstrap"
                    },
                    {
                        "name": "ReactQuery"
                    },
                    {
                        "name": "ReduxToolkit"
                    },
                    {
                        "name": "Webpack.config"
                    }
                ],
                "image": "/images/work/thumb1.png",
                "live": "https://panel.viracc.ir",
                "github": "https://github.com/sararmjalal"
            },
            {
                "num": "05",
                "category": "فرانت‌اند",
                "title": "Nikaat/home-landing",
                "description": "صفحه اصلی استاتیک از تمامی صفحات فرود (Nikaat-landing).",
                "stack": [
                    {
                        "name": "Typescript"
                    },
                    {
                        "name": "React"
                    },
                    {
                        "name": "Next"
                    },
                    {
                        "name": "MaterialUI"
                    },
                    {
                        "name": "GoogleAnalytics"
                    }
                ],
                "image": "/images/work/thumb1.png",
                "live": "https://matchadiet.com/",
                "github": "https://github.com/sararmjalal"
            },
            {
                "num": "04",
                "category": "فرانت‌اند",
                "title": "Nikaat/landing",
                "description": "یک کوییز ساده با استفاده از عناصر و استایل‌های ارائه‌شده توسط API که انواع مختلفی از کوییزها را از طریق URL ارائه می‌دهد.",
                "stack": [
                    {
                        "name": "Typescript"
                    },
                    {
                        "name": "React"
                    },
                    {
                        "name": "Next"
                    },
                    {
                        "name": "MaterialUI"
                    },
                    {
                        "name": "SWR"
                    },
                    {
                        "name": "Axios"
                    },
                    {
                        "name": "ReduxToolkit"
                    },
                    {
                        "name": "Wavesurfer"
                    },
                    {
                        "name": "GoogleAnalytics"
                    },
                    {
                        "name": "Hatjar"
                    }
                ],
                "image": "/images/work/thumb1.png",
                "live": "https://quiz.matchadiet.com?type=fit",
                "github": "https://github.com/sararmjalal"
            },
            {
                "num": "03",
                "category": "فرانت‌اند",
                "title": "E-commerce",
                "description": "یک اپلیکیشن تجارت الکترونیک با ویژگی‌های پایه مانند داشبورد مدیریت، داشبورد کاربر، خرید، سبد خرید و غیره.",
                "stack": [
                    {
                        "name": "TypeScript"
                    },
                    {
                        "name": "React"
                    },
                    {
                        "name": "Next"
                    },
                    {
                        "name": "ReactQuery"
                    },
                    {
                        "name": "React-hook-forms"
                    },
                    {
                        "name": "ReduxToolkit"
                    },
                    {
                        "name": "Tailwind"
                    }
                ],
                "image": "/images/work/thumb1.png",
                "live": "",
                "github": "https://github.com/Sararmjalal/ecommerce-final"
            },
            {
                "num": "02",
                "category": "فرانت‌اند",
                "title": "Blogext",
                "description": "یک اپلیکیشن وبلاگ ساده با استفاده از Next.js",
                "stack": [
                    {
                        "name": "React"
                    },
                    {
                        "name": "Next"
                    },
                    {
                        "name": "MaterialUI"
                    },
                    {
                        "name": "RESTfulAPI"
                    },
                    {
                        "name": "SWR"
                    },
                    {
                        "name": "ReduxToolkit"
                    },
                    {
                        "name": "TinyMCE"
                    }
                ],
                "image": "/images/work/thumb1.png",
                "live": "",
                "github": "https://github.com/Sararmjalal/blogext"
            },
            {
                "num": "01",
                "category": "فرانت‌اند",
                "title": "fineql",
                "description": "یک داشبورد مالی ساده با استفاده از GraphQL",
                "stack": [
                    {
                        "name": "React"
                    },
                    {
                        "name": "GraphQL"
                    },
                    {
                        "name": "ApolloProvider"
                    },
                    {
                        "name": "Tailwind"
                    },
                    {
                        "name": "Recharts"
                    },
                    {
                        "name": "ReactRouter"
                    },
                    {
                        "name": "ReactLeaflet"
                    }
                ],
                "image": "/images/work/thumb1.png",
                "live": "",
                "github": ""
            }
        ],
        "liveProjectTitle": "لایو پروژه",
        "gitRepoTitle": "ریپازیتوری گیتهاب"
    },
    "contact": {
        "title": "همکاری با من",
        "description": "",
        "selectPlaceholder": "یک سرویس انتخاب کنید",
        "select": [
            {
                "value": "fwd",
                "title": "توسعه وب فرانت‌اند"
            },
            {
                "value": "wpm",
                "title": "مدیریت محصول وب"
            },
            {
                "value": "wpd",
                "title": "توسعه وردپرس"
            },
            {
                "value": "grd",
                "title": "طراحی گرافیک"
            },
            {
                "value": "mtc",
                "title": "تدریس ریاضی"
            }
        ],
        "inputs": [
            {
                "type": "firstname",
                "placeholder": "نام"
            },
            {
                "type": "lastname",
                "placeholder": "نام خانوادگی"
            },
            {
                "type": "email",
                "placeholder": "آدرس ایمیل"
            },
            {
                "type": "phone",
                "placeholder": "شماره تلفن"
            }
        ],
        "textareaPlaceholder": "پیامتان را اینجا تایپ کنید...",
        "buttonText": "ارسال پیام",
        "info": [
            {
                "icon": "phone",
                "title": "تلفن",
                "description": "(98+) 903 134 6086"
            },
            {
                "icon": "email",
                "title": "ایمیل",
                "description": "Sara.jalal.115@gmail.com"
            },
            {
                "icon": "map",
                "title": "محل سکونت",
                "description": "تهران - ایران"
            }
        ]
    }
}